setup.cfg
setup.py
ol_commons_models/__init__.py
ol_commons_models/app.py
ol_commons_models/artemis.py
ol_commons_models/billing.py
ol_commons_models/logistics.py
ol_commons_models/rrhh.py
ol_commons_models/security.py
ol_commons_models_dev.egg-info/PKG-INFO
ol_commons_models_dev.egg-info/SOURCES.txt
ol_commons_models_dev.egg-info/dependency_links.txt
ol_commons_models_dev.egg-info/requires.txt
ol_commons_models_dev.egg-info/top_level.txt