Metadata-Version: 1.1
Name: ol-commons-models-dev
Version: 1.2.1
Summary: Paquete conteniente objetos reutilizables para los microservicios de OLYMPUS
Home-page: UNKNOWN
Author: Jean Pier Barbieri Rios
Author-email: jean.barbieri1996@gmail.com
License: UNKNOWN
Platform: UNKNOWN
Classifier: Development Status :: 5 - Production/Stable
Classifier: Intended Audience :: Information Technology
Classifier: License :: OSI Approved :: MIT License
